imess/init.py
imess/load.py
imess/run.py
imess-0.1.2.dist-info/LICENSE
imess-0.1.2.dist-info/METADATA
imess-0.1.2.dist-info/WHEEL
imess-0.1.2.dist-info/entry_points.txt
imess-0.1.2.dist-info/top_level.txt
imess-0.1.2.dist-info/RECORD
